nanofilm/__atom__.py
nanofilm/__exception__.py
nanofilm/__film__.py
nanofilm/__init__.py
nanofilm/__lattice__.py
nanofilm/__molecule__.py
nanofilm/__slab__.py
nanofilm/core.py
nanofilm-0.1.5.dist-info/METADATA
nanofilm-0.1.5.dist-info/WHEEL
nanofilm-0.1.5.dist-info/top_level.txt
nanofilm-0.1.5.dist-info/RECORD
