Metadata-Version: 2.1
Name: nanofilm
Version: 0.1.5
Summary: Manipulation of molecules adsorbed onto a substrate.
Home-page: https://github.com/rgaveiga/nanofilm
Author: Roberto Gomes de Aguiar Veiga
License: UNKNOWN
Platform: UNKNOWN
